web3utils/__init__.py
web3utils/chainstate.py
web3utils/constants.py
web3utils/contracts.py
web3utils/encodings.py
web3utils/monitors.py
web3utils/web3proxies.py
web3utils-0.1.3.dist-info/DESCRIPTION.rst
web3utils-0.1.3.dist-info/METADATA
web3utils-0.1.3.dist-info/RECORD
web3utils-0.1.3.dist-info/WHEEL
web3utils-0.1.3.dist-info/metadata.json
web3utils-0.1.3.dist-info/top_level.txt
