Metadata-Version: 2.0
Name: web3utils
Version: 0.1.3
Summary: Convenience tools for web3.py
Home-page: https://github.com/carver/web3utils.py
Author: Jason Carver
Author-email: ut96caarrs@snkmail.com
License: MIT
Keywords: ethereum eth web3 web3.py development library
Platform: UNKNOWN
Classifier: Development Status :: 3 - Alpha
Classifier: Intended Audience :: Developers
Classifier: Topic :: Database :: Front-Ends
Classifier: Topic :: Software Development :: Libraries
Classifier: Topic :: Security :: Cryptography
Classifier: Topic :: System :: Distributed Computing
Classifier: Topic :: Utilities
Classifier: License :: OSI Approved :: MIT License
Classifier: Programming Language :: Python :: 3
Classifier: Programming Language :: Python :: 3.5
Requires-Python: >=3.5
Requires-Dist: toolz (<1)
Requires-Dist: web3 (==3.11.1)
